.clang-format
.flake8
.gitignore
.gitmodules
CHANGELOG.md
CODEOWNERS
CODE_OF_CONDUCT
Dockerfile
Dockerfile-cuda
Dockerfile-embedded
LICENSE
MANIFEST.in
Makefile
README.md
__init__.py
description.txt
packages.txt
setup.py
./src/opendr/__init__.py
./src/opendr/_setup.py
./src/opendr/_version.py
./src/opendr/control/__init__.py
./src/opendr/engine/__init__.py
./src/opendr/engine/constants.py
./src/opendr/engine/data.py
./src/opendr/engine/datasets.py
./src/opendr/engine/example_learner.py
./src/opendr/engine/learners.py
./src/opendr/engine/target.py
./src/opendr/perception/__init__.py
./src/opendr/perception/heart_anomaly_detection/__init__.py
./src/opendr/perception/heart_anomaly_detection/dependencies.ini
./src/opendr/perception/heart_anomaly_detection/attention_neural_bag_of_feature/README.md
./src/opendr/perception/heart_anomaly_detection/attention_neural_bag_of_feature/__init__.py
./src/opendr/perception/heart_anomaly_detection/attention_neural_bag_of_feature/attention_neural_bag_of_feature_learner.py
./src/opendr/perception/heart_anomaly_detection/attention_neural_bag_of_feature/algorithm/__init__.py
./src/opendr/perception/heart_anomaly_detection/attention_neural_bag_of_feature/algorithm/models.py
./src/opendr/perception/heart_anomaly_detection/attention_neural_bag_of_feature/algorithm/samodels.py
./src/opendr/perception/heart_anomaly_detection/gated_recurrent_unit/README.md
./src/opendr/perception/heart_anomaly_detection/gated_recurrent_unit/__init__.py
./src/opendr/perception/heart_anomaly_detection/gated_recurrent_unit/gated_recurrent_unit_learner.py
./src/opendr/perception/heart_anomaly_detection/gated_recurrent_unit/algorithm/__init__.py
./src/opendr/perception/heart_anomaly_detection/gated_recurrent_unit/algorithm/data.py
./src/opendr/perception/heart_anomaly_detection/gated_recurrent_unit/algorithm/models.py
./src/opendr/perception/heart_anomaly_detection/gated_recurrent_unit/algorithm/trainers.py
./src/opendr/planning/__init__.py
./src/opendr_toolkit_heart_anomaly_detection.egg-info/PKG-INFO
./src/opendr_toolkit_heart_anomaly_detection.egg-info/SOURCES.txt
./src/opendr_toolkit_heart_anomaly_detection.egg-info/dependency_links.txt
./src/opendr_toolkit_heart_anomaly_detection.egg-info/requires.txt
./src/opendr_toolkit_heart_anomaly_detection.egg-info/top_level.txt
